[{"id": 1, "user": "rezajafari1365", "transfer": 3987}, {"id": 2, "user": "jarvis_sky", "transfer": 3583}, {"id": 3, "user": "test1", "transfer": 0}, {"id": 4, "user": "test2", "transfer": 0}, {"id": 5, "user": "parand", "transfer": 4679}, {"id": 6, "user": "ahad", "transfer": 3551}, {"id": 7, "user": "mortezaparsa", "transfer": 4509}, {"id": 8, "user": "fxmb1985", "transfer": 2938}, {"id": 9, "user": "Arash_kmangir", "transfer": 1219}, {"id": 10, "user": "Saeidfallahiii", "transfer": 1745}, {"id": 11, "user": "@masoodrezapoor", "transfer": 2146}, {"id": 12, "user": "Emad1194", "transfer": 2252}, {"id": 13, "user": "Mrm136900", "transfer": 3280}, {"id": 14, "user": "SadeqChaichi", "transfer": 2706}, {"id": 15, "user": "pangereha", "transfer": 3606}, {"id": 16, "user": "siraliresa", "transfer": 4485}, {"id": 17, "user": "arefm77", "transfer": 5353}, {"id": 18, "user": "Amin5shekarchi", "transfer": 2154}, {"id": 19, "user": "Mohammad_S3833", "transfer": 652}, {"id": 20, "user": "Irajsr69", "transfer": 1569}, {"id": 21, "user": "saeed714", "transfer": 735}, {"id": 22, "user": "farzadsarafrazi", "transfer": 0}, {"id": 23, "user": "EhsanMirjafari", "transfer": 1069}, {"id": 24, "user": "ZareiGh", "transfer": 4468}, {"id": 25, "user": "Ehsan1057", "transfer": 332}, {"id": 26, "user": "M_mahdikhanii", "transfer": 2049}, {"id": 27, "user": "saeidshabanzadehh", "transfer": 1439}, {"id": 28, "user": "hossein_dibapour", "transfer": 1415}, {"id": 29, "user": "yasamanghp", "transfer": 644}, {"id": 30, "user": "lilyzarin", "transfer": 2655}, {"id": 31, "user": "omid_vp2022", "transfer": 1577}, {"id": 32, "user": "pourestarabadi", "transfer": 1151}, {"id": 33, "user": "REZAARZPyMA", "transfer": 1371}, {"id": 34, "user": "ghaderianamir", "transfer": 5231}, {"id": 35, "user": "adelsahebkar", "transfer": 2971}, {"id": 36, "user": "xnds021", "transfer": 4313}, {"id": 37, "user": "Hamid_Roozegar", "transfer": 813}, {"id": 38, "user": "Arman_kasa", "transfer": 1385}, {"id": 39, "user": "Nikmanesh_E", "transfer": 0}, {"id": 40, "user": "NdsTraider", "transfer": 3931}, {"id": 41, "user": "amins59", "transfer": 4051}, {"id": 42, "user": "AK1265", "transfer": 1553}, {"id": 43, "user": "Saeed_Ah98", "transfer": 43}, {"id": 44, "user": "ghasem_darei", "transfer": 1699}, {"id": 45, "user": "Masoud_Mir_989", "transfer": 206}, {"id": 46, "user": "Mahdi_arghyani", "transfer": 1741}, {"id": 47, "user": "Eng_yunus", "transfer": 656}, {"id": 48, "user": "waveformliving", "transfer": 2682}, {"id": 49, "user": "Amirmohammadzadeh90", "transfer": 113}, {"id": 50, "user": "EPIFENI2022", "transfer": 1334}, {"id": 51, "user": "Iman_a1371", "transfer": 2401}, {"id": 52, "user": "Matwinter", "transfer": 0}, {"id": 53, "user": "mohamad7_ebrahimi", "transfer": 0}, {"id": 54, "user": "Rexan12345", "transfer": 3825}, {"id": 55, "user": "Khedri1366", "transfer": 466}, {"id": 56, "user": "Mahoorrrrrr00000", "transfer": 4354}, {"id": 57, "user": "hamidrezaasd", "transfer": 3445}, {"id": 58, "user": "HR19880", "transfer": 4116}, {"id": 59, "user": "Maryhkm", "transfer": 2660}, {"id": 60, "user": "Amoyaya", "transfer": 5310}, {"id": 61, "user": "amoradi110", "transfer": 334}, {"id": 62, "user": "bbaahhrr", "transfer": 3667}, {"id": 63, "user": "sanSABOR", "transfer": 1667}, {"id": 64, "user": "Masoud68ak", "transfer": 1910}, {"id": 65, "user": "makbarin", "transfer": 2351}, {"id": 66, "user": "Alirezarashiidii", "transfer": 1518}, {"id": 67, "user": "Omidansari_1", "transfer": 1746}, {"id": 68, "user": "MohseNaseri", "transfer": 3829}, {"id": 69, "user": "Minnoosh", "transfer": 3320}, {"id": 70, "user": "Dayaaaa", "transfer": 1122}, {"id": 71, "user": "ACMME", "transfer": 4962}, {"id": 72, "user": "mahmoudjal", "transfer": 3}, {"id": 73, "user": "saied79", "transfer": 1368}, {"id": 74, "user": "abred2018", "transfer": 0}, {"id": 75, "user": "Ho3n21", "transfer": 1499}, {"id": 76, "user": "Farzad_karampour", "transfer": 0}, {"id": 77, "user": "Omid_eng1", "transfer": 360}, {"id": 78, "user": "MIRKANI", "transfer": 501}, {"id": 79, "user": "HopeHoly", "transfer": 1362}, {"id": 80, "user": "reza1343", "transfer": 3104}, {"id": 81, "user": "mohammadi1622", "transfer": 2467}, {"id": 82, "user": "hossein_hf57", "transfer": 470}, {"id": 83, "user": "Amir_hosein_k", "transfer": 217}, {"id": 84, "user": "Imanba1994", "transfer": 1936}, {"id": 85, "user": "MR_REZV4N", "transfer": 159}, {"id": 86, "user": "smko_fz", "transfer": 372}, {"id": 87, "user": "hosseinzhmatkesh", "transfer": 2601}, {"id": 88, "user": "mj0902", "transfer": 3956}, {"id": 89, "user": "Farzrd", "transfer": 2766}, {"id": 90, "user": "Shahabspt", "transfer": 0}, {"id": 91, "user": "Farshadfattahii", "transfer": 4475}, {"id": 92, "user": "nobonlineshop", "transfer": 2115}, {"id": 93, "user": "Rfkm6470", "transfer": 1486}, {"id": 94, "user": "Aliafagh", "transfer": 3607}, {"id": 95, "user": "vahid2897", "transfer": 234}, {"id": 96, "user": "NDSJOB", "transfer": 1424}, {"id": 97, "user": "mojtaba5003", "transfer": 709}, {"id": 98, "user": "houshmandipour", "transfer": 1438}, {"id": 99, "user": "mkamali1351", "transfer": 3119}, {"id": 100, "user": "arad1998a", "transfer": 0}, {"id": 101, "user": "Meysambanazm", "transfer": 3046}, {"id": 102, "user": "behzad6058", "transfer": 1316}, {"id": 103, "user": "MMaahhii93", "transfer": 2224}, {"id": 104, "user": "Mohamadmousapour54", "transfer": 0}, {"id": 105, "user": "Hamid879296", "transfer": 6609}, {"id": 106, "user": "Iamrezajahangiri", "transfer": 1700}, {"id": 107, "user": "mnosrati1401", "transfer": 3052}, {"id": 108, "user": "nrz_sina", "transfer": 0}, {"id": 109, "user": "omidkh65n", "transfer": 2618}, {"id": 110, "user": "armanaria83", "transfer": 2058}, {"id": 111, "user": "alig2473", "transfer": 5}, {"id": 112, "user": "ZedZare", "transfer": 1433}, {"id": 113, "user": "alika2222", "transfer": 2308}, {"id": 114, "user": "AHE94", "transfer": 723}, {"id": 115, "user": "ArashFPD", "transfer": 20}, {"id": 116, "user": "e432hz", "transfer": 0}, {"id": 117, "user": "b_faezeh", "transfer": 1269}, {"id": 118, "user": "m2gh20", "transfer": 3779}, {"id": 119, "user": "Mammad_f69", "transfer": 3969}, {"id": 120, "user": "MahdiMashadi", "transfer": 3942}, {"id": 121, "user": "Bizhan1980", "transfer": 0}, {"id": 122, "user": "Mahdi_hoghoughi", "transfer": 4320}, {"id": 123, "user": "Hamidhastammmm", "transfer": 1827}, {"id": 124, "user": "Tiamde1", "transfer": 3826}, {"id": 125, "user": "ar_esmaeily", "transfer": 0}, {"id": 126, "user": "Just_NDS_Trading", "transfer": 4528}, {"id": 127, "user": "NDS_AR", "transfer": 252}, {"id": 128, "user": "PCjoy", "transfer": 2235}, {"id": 129, "user": "S_4_e_e_D", "transfer": 4119}, {"id": 130, "user": "royaa000", "transfer": 0}, {"id": 131, "user": "Scarf_shaparak", "transfer": 1488}, {"id": 132, "user": "Saeedw3", "transfer": 3997}, {"id": 133, "user": "mehrdad6699", "transfer": 186}, {"id": 134, "user": "Saghilogic", "transfer": 31}, {"id": 135, "user": "gh0o0stt", "transfer": 2231}, {"id": 136, "user": "reza_rdj", "transfer": 3887}, {"id": 137, "user": "Alivaghefi2810", "transfer": 19}, {"id": 138, "user": "Saeidsoltanipakdel", "transfer": 11}, {"id": 139, "user": "Amin136610", "transfer": 4024}, {"id": 140, "user": "Hani_Abdi", "transfer": 36}, {"id": 141, "user": "ShahramT", "transfer": 2314}, {"id": 142, "user": "powerfulallt", "transfer": 44}, {"id": 143, "user": "Amin_pk_1987", "transfer": 2223}, {"id": 144, "user": "mayan.soto", "transfer": 1387}, {"id": 145, "user": "Smrs1993", "transfer": 53}, {"id": 146, "user": "Hazara21", "transfer": 2899}, {"id": 147, "user": "mohmd_hs_1992", "transfer": 2318}, {"id": 148, "user": "Satainfo", "transfer": 2703}, {"id": 149, "user": "MRALIMPA", "transfer": 0}, {"id": 150, "user": "mrarman49", "transfer": 0}, {"id": 151, "user": "ehsanjahandideh", "transfer": 2620}, {"id": 152, "user": "Amin_gt3", "transfer": 0}, {"id": 153, "user": "Milmon", "transfer": 729}, {"id": 154, "user": "afshintalashan", "transfer": 3508}, {"id": 155, "user": "ffttbbh", "transfer": 0}, {"id": 156, "user": "amirho3ein66", "transfer": 0}, {"id": 157, "user": "ash4001", "transfer": 1910}, {"id": 158, "user": "naeem_malaeke", "transfer": 2538}, {"id": 159, "user": "Aran2022H", "transfer": 3451}, {"id": 160, "user": "mhmd80t", "transfer": 1405}, {"id": 161, "user": "shahriyargh2", "transfer": 2782}, {"id": 162, "user": "Mak1395", "transfer": 1750}, {"id": 163, "user": "nardokhte", "transfer": 458}, {"id": 164, "user": "greenro4d", "transfer": 0}, {"id": 165, "user": "Mahyargly2019", "transfer": 4252}, {"id": 166, "user": "miladone1", "transfer": 1496}, {"id": 167, "user": "saeed7ma", "transfer": 2557}, {"id": 168, "user": "Abolfazl_Sa72", "transfer": 2050}, {"id": 169, "user": "fuzzy_dark_matter", "transfer": 2287}, {"id": 170, "user": "Amatfard", "transfer": 35}, {"id": 171, "user": "Farshid_NDS", "transfer": 3780}, {"id": 172, "user": "Sallllllli", "transfer": 251}, {"id": 173, "user": "hojjatjahangiri", "transfer": 2685}, {"id": 174, "user": "Mehdi_i_71", "transfer": 3731}, {"id": 175, "user": "zahraa1374d", "transfer": 2598}, {"id": 176, "user": "Masoud5813", "transfer": 1025}, {"id": 177, "user": "Majid198273", "transfer": 1318}, {"id": 178, "user": "amirrezaghv", "transfer": 1452}, {"id": 179, "user": "ALIrezaFakhariyan", "transfer": 1163}, {"id": 180, "user": "EhSan22abx", "transfer": 1515}, {"id": 181, "user": "Jbboutiqo", "transfer": 206}, {"id": 182, "user": "Davood41245", "transfer": 1688}, {"id": 183, "user": "Fardinagh", "transfer": 4199}, {"id": 184, "user": "Niloofarazarfar", "transfer": 0}, {"id": 185, "user": "foroughbagheri2727", "transfer": 0}, {"id": 186, "user": "Asemani145", "transfer": 0}, {"id": 187, "user": "Smrjshkn", "transfer": 21}, {"id": 188, "user": "Amitici", "transfer": 2766}, {"id": 189, "user": "saeedkaramzadeh", "transfer": 1370}, {"id": 190, "user": "FANSIIR", "transfer": 204}, {"id": 191, "user": "Hossein5684", "transfer": 3262}, {"id": 192, "user": "FarhadMirshekar", "transfer": 0}, {"id": 193, "user": "Mr_ajam7", "transfer": 53}, {"id": 194, "user": "Smohammad1373", "transfer": 1500}, {"id": 195, "user": "Shahram_en65", "transfer": 969}, {"id": 196, "user": "hoseinjlv", "transfer": 1934}, {"id": 197, "user": "soojaf2017", "transfer": 2599}, {"id": 198, "user": "Zakiesobhani", "transfer": 1814}, {"id": 199, "user": "omidkhaaan", "transfer": 0}, {"id": 200, "user": "mohammad5512020", "transfer": 0}, {"id": 201, "user": "meysamasl", "transfer": 3}, {"id": 202, "user": "Mohamad_Nuri", "transfer": 3109}, {"id": 203, "user": "Sadegh_gharibi", "transfer": 178}, {"id": 204, "user": "Reza_Shkrlh", "transfer": 1476}, {"id": 205, "user": "mojitabapanahi1997", "transfer": 4876}, {"id": 206, "user": "farzad_h_z7", "transfer": 4575}, {"id": 207, "user": "mohsen9681", "transfer": 342}, {"id": 208, "user": "sarina_arsalan", "transfer": 1326}, {"id": 209, "user": "aliminji", "transfer": 704}, {"id": 210, "user": "MostafaEng", "transfer": 35}, {"id": 211, "user": "MR26am", "transfer": 1975}, {"id": 212, "user": "Dr_MAkhavan", "transfer": 3179}, {"id": 213, "user": "MeysamBaharami", "transfer": 5177}, {"id": 214, "user": "namdar19888", "transfer": 1128}, {"id": 215, "user": "msh00211", "transfer": 1030}, {"id": 216, "user": "Jam0611", "transfer": 2258}, {"id": 217, "user": "arminfth", "transfer": 2503}, {"id": 218, "user": "A_A0641", "transfer": 1535}, {"id": 219, "user": "AbdolmalekiOmidd", "transfer": 124}, {"id": 220, "user": "mehdigh6", "transfer": 1397}, {"id": 221, "user": "SA2572", "transfer": 2636}, {"id": 222, "user": "sami8000", "transfer": 3184}, {"id": 223, "user": "amirnaser56", "transfer": 3305}, {"id": 224, "user": "Xtrickyx", "transfer": 298}, {"id": 225, "user": "marigold51", "transfer": 0}, {"id": 226, "user": "MiladMohe6i", "transfer": 0}, {"id": 227, "user": "HJavdan", "transfer": 1451}, {"id": 228, "user": "Like_a_clock", "transfer": 951}, {"id": 229, "user": "Aliv2015", "transfer": 0}, {"id": 230, "user": "MPRJ89", "transfer": 929}, {"id": 231, "user": "pooriaorian", "transfer": 2655}, {"id": 232, "user": "hosseini_zs", "transfer": 1193}, {"id": 233, "user": "Ahmadsarvi", "transfer": 575}, {"id": 234, "user": "AfshinAsh", "transfer": 21}, {"id": 235, "user": "S_A_E_E_D_O_F", "transfer": 2459}, {"id": 236, "user": "Mohammad044444", "transfer": 77}, {"id": 237, "user": "Milad_4m", "transfer": 3830}, {"id": 238, "user": "Wahdat62", "transfer": 1561}, {"id": 239, "user": "akh_neja", "transfer": 4186}, {"id": 240, "user": "A_kianoush", "transfer": 1113}, {"id": 241, "user": "Laverite_desfaits", "transfer": 24}, {"id": 242, "user": "rezaei_1212122", "transfer": 2519}, {"id": 243, "user": "A_momayez", "transfer": 2708}, {"id": 244, "user": "Yaredabestani63", "transfer": 2422}, {"id": 245, "user": "Mona_m98", "transfer": 2653}, {"id": 246, "user": "mrntmmm", "transfer": 3355}, {"id": 247, "user": "RayRoy1972", "transfer": 1285}, {"id": 248, "user": "ArjomandiRH", "transfer": 2393}, {"id": 249, "user": "mj_vafaei", "transfer": 3069}, {"id": 250, "user": "sayyidabbasmohammadi", "transfer": 283}, {"id": 251, "user": "NAZERFAKHAR", "transfer": 2839}, {"id": 252, "user": "Ghalanimehdi", "transfer": 3903}, {"id": 253, "user": "Mohammadbarari09", "transfer": 615}, {"id": 254, "user": "v19951", "transfer": 137}, {"id": 255, "user": "the_mohammaad", "transfer": 652}, {"id": 256, "user": "Hossein0EA", "transfer": 224}, {"id": 257, "user": "hajkazemi55", "transfer": 2714}, {"id": 258, "user": "m_matroki", "transfer": 1480}, {"id": 259, "user": "Ali_fth1996", "transfer": 0}, {"id": 260, "user": "Thebrahimi", "transfer": 59}, {"id": 261, "user": "iransarzaminm", "transfer": 2472}, {"id": 262, "user": "Elii_Almasi", "transfer": 0}, {"id": 263, "user": "Hamid_2022_A", "transfer": 7}, {"id": 264, "user": "Soheil91628", "transfer": 0}, {"id": 265, "user": "Telemoj", "transfer": 2828}, {"id": 266, "user": "HosseiN_b73", "transfer": 0}, {"id": 267, "user": "kasrafallah", "transfer": 0}, {"id": 268, "user": "Naserfattahzadeh", "transfer": 1902}, {"id": 269, "user": "Saeedrazmkhah1", "transfer": 1470}, {"id": 270, "user": "hamid1350tjr", "transfer": 0}, {"id": 271, "user": "Omidfazayeli", "transfer": 678}, {"id": 272, "user": "tecsepideh", "transfer": 0}, {"id": 273, "user": "UZ1N2030", "transfer": 1954}, {"id": 274, "user": "faaarzad", "transfer": 0}, {"id": 275, "user": "Skipperarash", "transfer": 0}, {"id": 276, "user": "hilda_mobile", "transfer": 0}, {"id": 277, "user": "moh3en_r", "transfer": 229}, {"id": 278, "user": "erfan_rezae", "transfer": 168}, {"id": 279, "user": "Mihanzq", "transfer": 1283}, {"id": 280, "user": "reza_aba30", "transfer": 489}, {"id": 281, "user": "Xmajid24", "transfer": 228}, {"id": 282, "user": "rostam571", "transfer": 1956}, {"id": 283, "user": "Abolfazl_erfanian97", "transfer": 1289}, {"id": 284, "user": "aa1375tk", "transfer": 165}, {"id": 285, "user": "drmnz", "transfer": 0}, {"id": 286, "user": "Zhoozha0000", "transfer": 772}, {"id": 287, "user": "Pm_nikan", "transfer": 284}, {"id": 288, "user": "masoudhj1990", "transfer": 29}, {"id": 289, "user": "Hoseinnnnn", "transfer": 2124}, {"id": 290, "user": "Moshrefam", "transfer": 2918}, {"id": 291, "user": "Alioskoee", "transfer": 217}, {"id": 292, "user": "Mohsen1012033", "transfer": 1126}, {"id": 293, "user": "soheil_nrrr", "transfer": 3796}, {"id": 294, "user": "alimirxaei", "transfer": 1147}, {"id": 295, "user": "Mohammadchcbe", "transfer": 1959}, {"id": 296, "user": "avatar_id", "transfer": 0}, {"id": 297, "user": "alireza_logic", "transfer": 553}, {"id": 298, "user": "Vida135802", "transfer": 1195}, {"id": 299, "user": "Gfahavav23q1", "transfer": 0}, {"id": 300, "user": "Eiraheal", "transfer": 2093}, {"id": 301, "user": "mansour_z", "transfer": 3347}, {"id": 302, "user": "Kiarashpar", "transfer": 0}, {"id": 303, "user": "s_m8631", "transfer": 1276}, {"id": 304, "user": "fvkarimi", "transfer": 853}, {"id": 305, "user": "Mirror116", "transfer": 1321}, {"id": 306, "user": "mjdoust", "transfer": 1628}, {"id": 307, "user": "Hesamnt71", "transfer": 1073}, {"id": 308, "user": "alisahradoost", "transfer": 2534}, {"id": 309, "user": "re7so", "transfer": 123}, {"id": 310, "user": "Peyman_tak", "transfer": 0}, {"id": 311, "user": "eysun1991", "transfer": 0}, {"id": 312, "user": "Siamak1354khani", "transfer": 3155}, {"id": 313, "user": "rbmas193", "transfer": 3}, {"id": 314, "user": "Ams1366", "transfer": 118}, {"id": 315, "user": "Sajjad1471370", "transfer": 4174}, {"id": 316, "user": "A89777", "transfer": 0}, {"id": 317, "user": "reza_cheraqi", "transfer": 1069}, {"id": 318, "user": "ali1467p", "transfer": 2442}, {"id": 319, "user": "kh3384", "transfer": 1795}, {"id": 320, "user": "payam_hg", "transfer": 818}, {"id": 321, "user": "A12sghar", "transfer": 2175}, {"id": 322, "user": "mojmoda", "transfer": 3372}, {"id": 323, "user": "Nimafor", "transfer": 299}, {"id": 324, "user": "atran_perfume", "transfer": 0}, {"id": 325, "user": "mahdiyar_tx", "transfer": 1245}, {"id": 326, "user": "torkamanie", "transfer": 2327}, {"id": 327, "user": "msn_sa", "transfer": 2335}, {"id": 328, "user": "Emadgh27", "transfer": 1345}, {"id": 329, "user": "y5692w", "transfer": 1880}, {"id": 330, "user": "mkamalii", "transfer": 0}, {"id": 331, "user": "mehrana199", "transfer": 560}, {"id": 332, "user": "saavalan1200", "transfer": 4372}, {"id": 333, "user": "Pouriafarrokhi", "transfer": 827}, {"id": 334, "user": "Dean21sep", "transfer": 0}, {"id": 335, "user": "Nds_amini47", "transfer": 0}, {"id": 336, "user": "sattaei72", "transfer": 112}, {"id": 337, "user": "shadi7020hsm", "transfer": 1275}, {"id": 338, "user": "AliFathollahi", "transfer": 0}, {"id": 339, "user": "Benyamin_maleki71", "transfer": 2458}, {"id": 340, "user": "amiragh1983", "transfer": 1115}, {"id": 341, "user": "kave_usefi1993", "transfer": 0}, {"id": 342, "user": "ali_gtashari", "transfer": 102}, {"id": 343, "user": "mahtabnaderi2", "transfer": 222}, {"id": 344, "user": "Moha0613", "transfer": 16}, {"id": 345, "user": "aliamn98", "transfer": 0}, {"id": 346, "user": "BehzadGogonani", "transfer": 839}, {"id": 347, "user": "DBMBR", "transfer": 0}, {"id": 348, "user": "hamidsedaghts", "transfer": 904}, {"id": 349, "user": "mahmaz2", "transfer": 0}, {"id": 350, "user": "Mo_planet", "transfer": 124}, {"id": 351, "user": "Ehsaniehsani1515", "transfer": 0}, {"id": 352, "user": "Amir_80988", "transfer": 6363}, {"id": 353, "user": "mpb0281984", "transfer": 4}, {"id": 354, "user": "hsm_p44", "transfer": 1656}, {"id": 355, "user": "mahbod20", "transfer": 0}, {"id": 356, "user": "b6rmi", "transfer": 0}, {"id": 357, "user": "Omid1440", "transfer": 1626}, {"id": 358, "user": "h_mashayekh97", "transfer": 232}, {"id": 359, "user": "unqfore", "transfer": 13}, {"id": 360, "user": "Ehteshaminiya", "transfer": 1741}, {"id": 361, "user": "Naliizadehh", "transfer": 285}, {"id": 362, "user": "nds_strategy_1", "transfer": 1347}, {"id": 363, "user": "ABBASshiir", "transfer": 3}, {"id": 364, "user": "Morteza2828", "transfer": 1930}, {"id": 365, "user": "ABDOLREZA_AMINZADEH", "transfer": 0}, {"id": 366, "user": "mfarzin", "transfer": 3}, {"id": 367, "user": "nejali", "transfer": 1297}, {"id": 368, "user": "MeysamPars", "transfer": 0}, {"id": 369, "user": "mohammadian_1360", "transfer": 1709}, {"id": 370, "user": "ahoora13879", "transfer": 855}, {"user": "Airoop", "transfer": 0}]